[
    [
        {
            "id": "briar",
            "name": "Briar",
            "img_url": "tft17_briar.tft_set17.png"
        },
        {
            "id": "cho'gath",
            "name": "Cho'Gath",
            "img_url": "tft17_chogath.tft_set17.png"
        },
        {
            "id": "ezreal",
            "name": "Ezreal",
            "img_url": "tft17_ezreal.tft_set17.png"
        },
        {
            "id": "leona",
            "name": "Leona",
            "img_url": "tft17_leona.tft_set17.png"
        },
        {
            "id": "lissandra",
            "name": "Lissandra",
            "img_url": "tft17_lissandra.tft_set17.png"
        },
        {
            "id": "poppy",
            "name": "Poppy",
            "img_url": "tft17_poppy.tft_set17.png"
        },
        {
            "id": "rek'sai",
            "name": "Rek'Sai",
            "img_url": "tft17_reksai.tft_set17.png"
        },
        {
            "id": "talon",
            "name": "Talon",
            "img_url": "tft17_talon.tft_set17.png"
        },
        {
            "id": "teemo",
            "name": "Teemo",
            "img_url": "tft17_teemo.tft_set17.png"
        },
        {
            "id": "twisted_fate",
            "name": "Twisted Fate",
            "img_url": "tft17_twistedfate.tft_set17.png"
        },
        {
            "id": "veigar",
            "name": "Veigar",
            "img_url": "tft17_veigar.tft_set17.png"
        }
    ],
    [
        {
            "id": "akali",
            "name": "Akali",
            "img_url": "tft17_akali.tft_set17.png"
        },
        {
            "id": "bel'veth",
            "name": "Bel'Veth",
            "img_url": "tft17_belveth.tft_set17.png"
        },
        {
            "id": "gwen",
            "name": "Gwen",
            "img_url": "tft17_gwen.tft_set17.png"
        },
        {
            "id": "jax",
            "name": "Jax",
            "img_url": "tft17_jax.tft_set17.png"
        },
        {
            "id": "pantheon",
            "name": "Pantheon",
            "img_url": "tft17_pantheon.tft_set17.png"
        },
        {
            "id": "pyke",
            "name": "Pyke",
            "img_url": "tft17_pyke.tft_set17.png"
        },
        {
            "id": "zoe",
            "name": "Zoe",
            "img_url": "tft17_zoe.tft_set17.png"
        }
    ],
    [
        {
            "id": "aurora",
            "name": "Aurora",
            "img_url": "tft17_aurora.tft_set17.png"
        },
        {
            "id": "diana",
            "name": "Diana",
            "img_url": "tft17_diana_teamplanner_splash.tft_set17.png"
        },
        {
            "id": "fizz",
            "name": "Fizz",
            "img_url": "tft17_fizz.tft_set17.png"
        },
        {
            "id": "illaoi",
            "name": "Illaoi",
            "img_url": "tft17_illaoi.tft_set17.png"
        },
        {
            "id": "kai'sa",
            "name": "Kai'Sa",
            "img_url": "tft17_kaisa.tft_set17.png"
        },
        {
            "id": "lulu",
            "name": "Lulu",
            "img_url": "tft17_lulu.tft_set17.png"
        },
        {
            "id": "maokai",
            "name": "Maokai",
            "img_url": "tft17_maokai.tft_set17.png"
        },
        {
            "id": "ornn",
            "name": "Ornn",
            "img_url": "tft17_ornn.tft_set17.png"
        },
        {
            "id": "viktor",
            "name": "Viktor",
            "img_url": "tft17_viktor.tft_set17.png"
        }
    ],
    [
        {
            "id": "aurelion_sol",
            "name": "Aurelion Sol",
            "img_url": "tft17_aurelionsol.tft_set17.png"
        },
        {
            "id": "corki",
            "name": "Corki",
            "img_url": "tft17_corki.tft_set17.png"
        },
        {
            "id": "karma",
            "name": "Karma",
            "img_url": "tft17_karma.tft_set17.png"
        },
        {
            "id": "kindred",
            "name": "Kindred",
            "img_url": "tft17_kindred.tft_set17.png"
        },
        {
            "id": "leblanc",
            "name": "LeBlanc",
            "img_url": "tft17_leblanc.tft_set17.png"
        },
        {
            "id": "master_yi",
            "name": "Master Yi",
            "img_url": "tft17_masteryi.tft_set17.png"
        },
        {
            "id": "nami",
            "name": "Nami",
            "img_url": "tft17_nami.tft_set17.png"
        },
        {
            "id": "nunu_&_willump",
            "name": "Nunu & Willump",
            "img_url": "tft17_nunu.tft_set17.png"
        },
        {
            "id": "rammus",
            "name": "Rammus",
            "img_url": "tft17_rammus.tft_set17.png"
        },
        {
            "id": "riven",
            "name": "Riven",
            "img_url": "tft17_riven.tft_set17.png"
        },
        {
            "id": "tahm_kench",
            "name": "Tahm Kench",
            "img_url": "tft17_tahmkench.tft_set17.png"
        },
        {
            "id": "the_mighty_mech",
            "name": "The Mighty Mech",
            "img_url": "tft17_galio.tft_set17.png"
        },
        {
            "id": "xayah",
            "name": "Xayah",
            "img_url": "tft17_xayah.tft_set17.png"
        }
    ],
    [
        {
            "id": "bard",
            "name": "Bard",
            "img_url": "tft17_bard.tft_set17.png"
        },
        {
            "id": "fiora",
            "name": "Fiora",
            "img_url": "tft17_fiora.tft_set17.png"
        },
        {
            "id": "graves",
            "name": "Graves",
            "img_url": "tft17_graves.tft_set17.png"
        },
        {
            "id": "jhin",
            "name": "Jhin",
            "img_url": "tft17_jhin.tft_set17.png"
        },
        {
            "id": "vex",
            "name": "Vex",
            "img_url": "tft17_vex.tft_set17.png"
        }
    ]
]